factorialhr/__init__.py
factorialhr/_api_public.py
factorialhr/_ats.py
factorialhr/_attendance.py
factorialhr/_banking.py
factorialhr/_bookkeepers_management.py
factorialhr/_client.py
factorialhr/_companies.py
factorialhr/_contracts.py
factorialhr/_custom_fields.py
factorialhr/_custom_resources.py
factorialhr/_documents.py
factorialhr/_employee_updates.py
factorialhr/_employees.py
factorialhr/_expenses.py
factorialhr/_finance.py
factorialhr/_holidays.py
factorialhr/_job_catalog.py
factorialhr/_locations.py
factorialhr/_marketplace.py
factorialhr/_payroll.py
factorialhr/_payroll_employees.py
factorialhr/_payroll_integrations_base.py
factorialhr/_performance.py
factorialhr/_posts.py
factorialhr/_project_management.py
factorialhr/_shift_management.py
factorialhr/_tasks.py
factorialhr/_teams.py
factorialhr/_time_planning.py
factorialhr/_time_settings.py
factorialhr/_timeoff.py
factorialhr/_trainings.py
factorialhr/_work_schedule.py
factorialhr/py.typed
factorialhr/_cli/__init__.py
factorialhr/_cli/access_token.py
factorialhr/_cli/account.py
factorialhr/_cli/common.py
factorialhr/_cli/http_server.py
factorialhr/_cli/projects.py
factorialhr-4.1.0.dist-info/METADATA
factorialhr-4.1.0.dist-info/WHEEL
factorialhr-4.1.0.dist-info/entry_points.txt
factorialhr-4.1.0.dist-info/licenses/LICENSE
factorialhr-4.1.0.dist-info/RECORD
