Metadata-Version: 2.4
Name: factorialhr
Version: 4.1.0
Summary: Python package for the api of FactorialHR
Project-URL: Repository, https://github.com/leon1995/factorialhr
Project-URL: Bug Tracker, https://github.com/leon1995/factorialhr/issues
Author-email: Leon Budnick <y6q6ea9w@mail-proxy.org>
License-File: LICENSE
Keywords: FactorialHR,HR
Classifier: Development Status :: 5 - Production/Stable
Classifier: Intended Audience :: Developers
Classifier: Intended Audience :: End Users/Desktop
Classifier: License :: OSI Approved :: GNU Affero General Public License v3
Classifier: Operating System :: OS Independent
Classifier: Programming Language :: Python :: 3
Classifier: Programming Language :: Python :: 3.11
Classifier: Programming Language :: Python :: 3.12
Classifier: Programming Language :: Python :: 3.13
Classifier: Topic :: Office/Business
Requires-Python: <3.14,>=3.11
Requires-Dist: anyio>=4.7.0
Requires-Dist: httpx>=0.28.1
Requires-Dist: pydantic>=2.10.6
Provides-Extra: cli
Requires-Dist: aiohttp>=3.11.12; extra == 'cli'
Requires-Dist: cloup>=3.0.6; extra == 'cli'
Requires-Dist: polars>=1.27.1; extra == 'cli'
Requires-Dist: python-dateutil>=2.9.0; extra == 'cli'
Requires-Dist: tabulate>=0.9.0; extra == 'cli'
